hoottit/__init__.py
hoottit/__main__.py
hoottit/consumers.py
hoottit/producers.py
hoottit/util.py
hoottit-0.1.dev0.dist-info/DESCRIPTION.rst
hoottit-0.1.dev0.dist-info/METADATA
hoottit-0.1.dev0.dist-info/RECORD
hoottit-0.1.dev0.dist-info/WHEEL
hoottit-0.1.dev0.dist-info/entry_points.txt
hoottit-0.1.dev0.dist-info/metadata.json
hoottit-0.1.dev0.dist-info/top_level.txt
