Metadata-Version: 2.0
Name: hoottit
Version: 0.1.dev0
Summary: Simple tool that caches Reddit submissions and comments
Home-page: https://github.com/Owlree/hoottit
Author: Robert Badea
Author-email: owlree128@gmail.com
License: MIT License
